littlegit.py
littlegit-0.2.0.dist-info/LICENSE
littlegit-0.2.0.dist-info/METADATA
littlegit-0.2.0.dist-info/WHEEL
littlegit-0.2.0.dist-info/top_level.txt
littlegit-0.2.0.dist-info/RECORD
