Metadata-Version: 2.1
Name: littlegit
Version: 0.2.0
Summary: This is a little tiny wrapper around Git CLI
Home-page: https://github.com/expobrain/littlegit
Author: Daniele Esposti
Author-email: daniele.esposti@gmail.com
License: MIT
Platform: UNKNOWN
Classifier: License :: Public Domain
Classifier: Development Status :: 5 - Production/Stable
Classifier: Operating System :: OS Independent
Classifier: Programming Language :: Python :: 3
Classifier: Intended Audience :: Developers
Classifier: Topic :: System
Classifier: Topic :: Internet
Classifier: Topic :: Software Development :: Libraries
